pypyt/__init__.py
pypyt/html_docs/api.html
pypyt/html_docs/docs.html
pypyt/html_docs/genindex.html
pypyt/html_docs/index.html
pypyt/html_docs/objects.inv
pypyt/html_docs/py-modindex.html
pypyt/html_docs/search.html
pypyt/html_docs/searchindex.js
pypyt/html_docs/use.html
pypyt/html_docs/_images/output1.png
pypyt/html_docs/_images/output2.png
pypyt/html_docs/_images/output3.png
pypyt/html_docs/_images/output4.png
pypyt/html_docs/_images/template1.png
pypyt/html_docs/_images/template2.png
pypyt/html_docs/_images/template3.png
pypyt/html_docs/_images/template4.png
pypyt/html_docs/_sources/api.rst.txt
pypyt/html_docs/_sources/docs.md.txt
pypyt/html_docs/_sources/index.rst.txt
pypyt/html_docs/_sources/use.rst.txt
pypyt/html_docs/_static/agogo.css
pypyt/html_docs/_static/ajax-loader.gif
pypyt/html_docs/_static/alabaster.css
pypyt/html_docs/_static/basic.css
pypyt/html_docs/_static/bgfooter.png
pypyt/html_docs/_static/bgtop.png
pypyt/html_docs/_static/classic.css
pypyt/html_docs/_static/comment-bright.png
pypyt/html_docs/_static/comment-close.png
pypyt/html_docs/_static/comment.png
pypyt/html_docs/_static/custom.css
pypyt/html_docs/_static/doctools.js
pypyt/html_docs/_static/documentation_options.js
pypyt/html_docs/_static/down-pressed.png
pypyt/html_docs/_static/down.png
pypyt/html_docs/_static/file.png
pypyt/html_docs/_static/jquery-3.2.1.js
pypyt/html_docs/_static/jquery.js
pypyt/html_docs/_static/minus.png
pypyt/html_docs/_static/nature.css
pypyt/html_docs/_static/plus.png
pypyt/html_docs/_static/pygments.css
pypyt/html_docs/_static/searchtools.js
pypyt/html_docs/_static/sidebar.js
pypyt/html_docs/_static/underscore-1.3.1.js
pypyt/html_docs/_static/underscore.js
pypyt/html_docs/_static/up-pressed.png
pypyt/html_docs/_static/up.png
pypyt/html_docs/_static/websupport.js
pypyt/html_docs/_static/css/badge_only.css
pypyt/html_docs/_static/css/theme.css
pypyt/html_docs/_static/fonts/Inconsolata-Bold.ttf
pypyt-0.0.6.dist-info/METADATA
pypyt-0.0.6.dist-info/RECORD
pypyt-0.0.6.dist-info/WHEEL
pypyt-0.0.6.dist-info/top_level.txt
