Metadata-Version: 2.1
Name: pypyt
Version: 0.0.6
Summary: Simple library to render ppt templates in python
Home-page: https://gitlab.criteois.com/j.gajardo/pypyt
Author: Julio Gajardo
Author-email: j.gajardo@criteo.com
License: MIT
Platform: UNKNOWN
Requires-Dist: python-pptx
